ykenan_log/__init__.py
ykenan_log-0.2.5.dist-info/METADATA
ykenan_log-0.2.5.dist-info/WHEEL
ykenan_log-0.2.5.dist-info/licenses/LICENSE
ykenan_log-0.2.5.dist-info/RECORD
