Metadata-Version: 2.4
Name: ykenan_log
Version: 0.2.5
Summary: Log information: Print the log, export the log file.
Project-URL: github, https://github.com/YuZhengM/ykenan_log
Author-email: Zhengmin Yu <yuzmbio@163.com>
License: Copyright (c) 2023 YKenan
License-File: LICENSE
Keywords: YKenan,file,log
Classifier: License :: OSI Approved :: MIT License
Classifier: Operating System :: OS Independent
Classifier: Programming Language :: Python :: 3
Requires-Python: >=3.9
Requires-Dist: coloredlogs>=15.0
